tencentcos_storage/__init__.py
tencentcos_storage/file.py
tencentcos_storage/storage.py
django_cos_storage-0.5.7.dist-info/LICENSE
django_cos_storage-0.5.7.dist-info/WHEEL
django_cos_storage-0.5.7.dist-info/METADATA
django_cos_storage-0.5.7.dist-info/RECORD
