Metadata-Version: 2.1
Name: django-cos-storage
Version: 0.5.7
Summary: A django app for Tencent Cloud Object Storage. 腾讯云对象存储（COS）服务 for Django。
Home-page: https://github.com/jukanntenn/django-tencentcos-storage
License: BSD-3-Clause
Keywords: django
Author: jukanntenn
Author-email: jukanntenn@outlook.com
Requires-Python: >=3.7,<4.0
Classifier: License :: OSI Approved :: BSD License
Classifier: Programming Language :: Python :: 3
Classifier: Programming Language :: Python :: 3.10
Classifier: Programming Language :: Python :: 3.7
Classifier: Programming Language :: Python :: 3.8
Classifier: Programming Language :: Python :: 3.9
Requires-Dist: cos-python-sdk-v5 (>=1.9.4,<2.0.0)
Project-URL: Repository, https://github.com/jukanntenn/django-tencentcos-storage
